<Experiment>
<Problem name = 'MONRP_50_4_5_0_90 100'>
<Algorithm name = 'NSGAII'>
<Run id = '1'>
<Summary>
<NumEvals>4000</NumEvals>
<RunTime>52.2605659962</RunTime>
<IBD>1.35138652608</IBD>
<IBS>0.0184852415786</IBS>
<f1>95589.0</f1>
<f2>488.0</f2>
<f3>99560.0</f3>
</Summary></Run>
<Run id = '2'>
<Summary>
<NumEvals>4000</NumEvals>
<RunTime>35.2702240944</RunTime>
<IBD>1.35295613528</IBD>
<IBS>0.0448376675683</IBS>
<f1>95762.0</f1>
<f2>469.0</f2>
<f3>99574.0</f3>
</Summary></Run>
<Run id = '3'>
<Summary>
<NumEvals>4000</NumEvals>
<RunTime>133.369959831</RunTime>
<IBD>1.34946075878</IBD>
<IBS>0.0338289379834</IBS>
<f1>96286.0</f1>
<f2>457.0</f2>
<f3>99630.0</f3>
</Summary></Run>
<Run id = '4'>
<Summary>
<NumEvals>4000</NumEvals>
<RunTime>43.775398016</RunTime>
<IBD>1.34217411109</IBD>
<IBS>0.0262924309534</IBS>
<f1>95975.0</f1>
<f2>454.0</f2>
<f3>99588.0</f3>
</Summary></Run>
<Run id = '5'>
<Summary>
<NumEvals>4000</NumEvals>
<RunTime>51.3432750702</RunTime>
<IBD>1.35296598713</IBD>
<IBS>0.0307406526579</IBS>
<f1>95999.0</f1>
<f2>461.0</f2>
<f3>99567.0</f3>
</Summary></Run>
<Run id = '6'>
<Summary>
<NumEvals>4000</NumEvals>
<RunTime>57.1372020245</RunTime>
<IBD>1.34226250792</IBD>
<IBS>0.0235732745196</IBS>
<f1>95798.0</f1>
<f2>476.0</f2>
<f3>99571.0</f3>
</Summary></Run>
<Run id = '7'>
<Summary>
<NumEvals>4000</NumEvals>
<RunTime>16.6909909248</RunTime>
<IBD>1.3460438096</IBD>
<IBS>0.0244620361192</IBS>
<f1>96245.0</f1>
<f2>443.0</f2>
<f3>99586.0</f3>
</Summary></Run>
<Run id = '8'>
<Summary>
<NumEvals>4000</NumEvals>
<RunTime>35.2893929482</RunTime>
<IBD>1.3399485243</IBD>
<IBS>0.0328192739443</IBS>
<f1>96091.0</f1>
<f2>436.0</f2>
<f3>99610.0</f3>
</Summary></Run>
<Run id = '9'>
<Summary>
<NumEvals>4000</NumEvals>
<RunTime>50.117429018</RunTime>
<IBD>1.34099540881</IBD>
<IBS>0.029872140727</IBS>
<f1>96029.0</f1>
<f2>440.0</f2>
<f3>99583.0</f3>
</Summary></Run>
<Run id = '10'>
<Summary>
<NumEvals>4000</NumEvals>
<RunTime>102.010226011</RunTime>
<IBD>1.34521114144</IBD>
<IBS>0.0377369065324</IBS>
<f1>95564.0</f1>
<f2>456.0</f2>
<f3>99577.0</f3>
</Summary></Run>
</Algorithm>
<Algorithm name = 'SPEA2'>
<Run id = '1'>
<Summary>
<NumEvals>4000</NumEvals>
<RunTime>29.6855611801</RunTime>
<IBD>1.34788046308</IBD>
<IBS>0.0330011021361</IBS>
<f1>95987.0</f1>
<f2>443.0</f2>
<f3>99603.0</f3>
</Summary></Run>
<Run id = '2'>
<Summary>
<NumEvals>4000</NumEvals>
<RunTime>71.2084879875</RunTime>
<IBD>1.34383948726</IBD>
<IBS>0.027679328583</IBS>
<f1>95869.0</f1>
<f2>446.0</f2>
<f3>99594.0</f3>
</Summary></Run>
<Run id = '3'>
<Summary>
<NumEvals>4000</NumEvals>
<RunTime>109.747170925</RunTime>
<IBD>1.34120436456</IBD>
<IBS>0.0418583058565</IBS>
<f1>96508.0</f1>
<f2>407.0</f2>
<f3>99652.0</f3>
</Summary></Run>
<Run id = '4'>
<Summary>
<NumEvals>4000</NumEvals>
<RunTime>110.702996969</RunTime>
<IBD>1.35382610648</IBD>
<IBS>0.0294886705252</IBS>
<f1>95617.0</f1>
<f2>448.0</f2>
<f3>99575.0</f3>
</Summary></Run>
<Run id = '5'>
<Summary>
<NumEvals>4000</NumEvals>
<RunTime>131.753429174</RunTime>
<IBD>1.35248680204</IBD>
<IBS>0.0240852899215</IBS>
<f1>95712.0</f1>
<f2>455.0</f2>
<f3>99570.0</f3>
</Summary></Run>
<Run id = '6'>
<Summary>
<NumEvals>4000</NumEvals>
<RunTime>129.546647787</RunTime>
<IBD>1.35482176157</IBD>
<IBS>0.0326125680956</IBS>
<f1>95827.0</f1>
<f2>460.0</f2>
<f3>99593.0</f3>
</Summary></Run>
<Run id = '7'>
<Summary>
<NumEvals>4000</NumEvals>
<RunTime>66.1183669567</RunTime>
<IBD>1.35120555143</IBD>
<IBS>0.0240288928556</IBS>
<f1>95837.0</f1>
<f2>456.0</f2>
<f3>99611.0</f3>
</Summary></Run>
<Run id = '8'>
<Summary>
<NumEvals>4000</NumEvals>
<RunTime>101.851756096</RunTime>
<IBD>1.35176540493</IBD>
<IBS>0.0253566249899</IBS>
<f1>96193.0</f1>
<f2>425.0</f2>
<f3>99604.0</f3>
</Summary></Run>
<Run id = '9'>
<Summary>
<NumEvals>4000</NumEvals>
<RunTime>86.5310418606</RunTime>
<IBD>1.35296422496</IBD>
<IBS>0.0305419944236</IBS>
<f1>96324.0</f1>
<f2>439.0</f2>
<f3>99633.0</f3>
</Summary></Run>
<Run id = '10'>
<Summary>
<NumEvals>4000</NumEvals>
<RunTime>142.253875017</RunTime>
<IBD>1.35580195881</IBD>
<IBS>0.029421136829</IBS>
<f1>95988.0</f1>
<f2>442.0</f2>
<f3>99593.0</f3>
</Summary></Run>
</Algorithm>
</Problem>
<Problem name = 'MONRP_50_4_5_0_110 100'>
<Algorithm name = 'NSGAII'>
<Run id = '1'>
<Summary>
<NumEvals>4000</NumEvals>
<RunTime>18.4894559383</RunTime>
<IBD>1.349209832</IBD>
<IBS>0.030002506174</IBS>
<f1>97131.0</f1>
<f2>452.0</f2>
<f3>99596.0</f3>
</Summary></Run>
<Run id = '2'>
<Summary>
<NumEvals>4000</NumEvals>
<RunTime>16.3384358883</RunTime>
<IBD>1.35497806092</IBD>
<IBS>0.0270259594534</IBS>
<f1>96997.0</f1>
<f2>483.0</f2>
<f3>99577.0</f3>
</Summary></Run>
<Run id = '3'>
<Summary>
<NumEvals>4000</NumEvals>
<RunTime>51.0685679913</RunTime>
<IBD>1.36248015542</IBD>
<IBS>0.017269939367</IBS>
<f1>96444.0</f1>
<f2>499.0</f2>
<f3>99560.0</f3>
</Summary></Run>
<Run id = '4'>
<Summary>
<NumEvals>4000</NumEvals>
<RunTime>12.7716360092</RunTime>
<IBD>1.35261618936</IBD>
<IBS>0.0279003412588</IBS>
<f1>97182.0</f1>
<f2>474.0</f2>
<f3>99594.0</f3>
</Summary></Run>
<Run id = '5'>
<Summary>
<NumEvals>4000</NumEvals>
<RunTime>9.55074501038</RunTime>
<IBD>1.35065269497</IBD>
<IBS>0.0253963386131</IBS>
<f1>96953.0</f1>
<f2>469.0</f2>
<f3>99587.0</f3>
</Summary></Run>
<Run id = '6'>
<Summary>
<NumEvals>4000</NumEvals>
<RunTime>17.2906110287</RunTime>
<IBD>1.34777591377</IBD>
<IBS>0.0140991166004</IBS>
<f1>96932.0</f1>
<f2>483.0</f2>
<f3>99577.0</f3>
</Summary></Run>
<Run id = '7'>
<Summary>
<NumEvals>4000</NumEvals>
<RunTime>11.7222771645</RunTime>
<IBD>1.35911609831</IBD>
<IBS>0.0281241625427</IBS>
<f1>96787.0</f1>
<f2>461.0</f2>
<f3>99587.0</f3>
</Summary></Run>
<Run id = '8'>
<Summary>
<NumEvals>4000</NumEvals>
<RunTime>12.6124081612</RunTime>
<IBD>1.35857208906</IBD>
<IBS>0.0231435949832</IBS>
<f1>97234.0</f1>
<f2>486.0</f2>
<f3>99581.0</f3>
</Summary></Run>
<Run id = '9'>
<Summary>
<NumEvals>4000</NumEvals>
<RunTime>24.8410820961</RunTime>
<IBD>1.3545599309</IBD>
<IBS>0.020702836798</IBS>
<f1>96594.0</f1>
<f2>500.0</f2>
<f3>99563.0</f3>
</Summary></Run>
<Run id = '10'>
<Summary>
<NumEvals>4000</NumEvals>
<RunTime>5.36850595474</RunTime>
<IBD>1.34956190051</IBD>
<IBS>0.0157157638197</IBS>
<f1>97105.0</f1>
<f2>466.0</f2>
<f3>99589.0</f3>
</Summary></Run>
</Algorithm>
<Algorithm name = 'SPEA2'>
<Run id = '1'>
<Summary>
<NumEvals>4000</NumEvals>
<RunTime>17.4809641838</RunTime>
<IBD>1.35048106939</IBD>
<IBS>0.03002652202</IBS>
<f1>96829.0</f1>
<f2>452.0</f2>
<f3>99599.0</f3>
</Summary></Run>
<Run id = '2'>
<Summary>
<NumEvals>4000</NumEvals>
<RunTime>46.3082659245</RunTime>
<IBD>1.35538883084</IBD>
<IBS>0.0222858954094</IBS>
<f1>96939.0</f1>
<f2>462.0</f2>
<f3>99584.0</f3>
</Summary></Run>
<Run id = '3'>
<Summary>
<NumEvals>4000</NumEvals>
<RunTime>28.5425598621</RunTime>
<IBD>1.3533196766</IBD>
<IBS>0.0328130539724</IBS>
<f1>97327.0</f1>
<f2>420.0</f2>
<f3>99617.0</f3>
</Summary></Run>
<Run id = '4'>
<Summary>
<NumEvals>4000</NumEvals>
<RunTime>32.9454441071</RunTime>
<IBD>1.35246439282</IBD>
<IBS>0.0296274503735</IBS>
<f1>97110.0</f1>
<f2>453.0</f2>
<f3>99603.0</f3>
</Summary></Run>
<Run id = '5'>
<Summary>
<NumEvals>4000</NumEvals>
<RunTime>28.2948689461</RunTime>
<IBD>1.35682544123</IBD>
<IBS>0.0264149825001</IBS>
<f1>97275.0</f1>
<f2>446.0</f2>
<f3>99614.0</f3>
</Summary></Run>
<Run id = '6'>
<Summary>
<NumEvals>4000</NumEvals>
<RunTime>13.3102588654</RunTime>
<IBD>1.34465040863</IBD>
<IBS>0.0285958393491</IBS>
<f1>97230.0</f1>
<f2>439.0</f2>
<f3>99609.0</f3>
</Summary></Run>
<Run id = '7'>
<Summary>
<NumEvals>4000</NumEvals>
<RunTime>33.9980251789</RunTime>
<IBD>1.35033191995</IBD>
<IBS>0.0269526527628</IBS>
<f1>97454.0</f1>
<f2>433.0</f2>
<f3>99625.0</f3>
</Summary></Run>
<Run id = '8'>
<Summary>
<NumEvals>4000</NumEvals>
<RunTime>61.7349200249</RunTime>
<IBD>1.35236469674</IBD>
<IBS>0.0278651878832</IBS>
<f1>97158.0</f1>
<f2>448.0</f2>
<f3>99610.0</f3>
</Summary></Run>
<Run id = '9'>
<Summary>
<NumEvals>4000</NumEvals>
<RunTime>39.8563210964</RunTime>
<IBD>1.35572916189</IBD>
<IBS>0.0194744720222</IBS>
<f1>96953.0</f1>
<f2>463.0</f2>
<f3>99589.0</f3>
</Summary></Run>
<Run id = '10'>
<Summary>
<NumEvals>4000</NumEvals>
<RunTime>25.8577148914</RunTime>
<IBD>1.35667719877</IBD>
<IBS>0.0299927605055</IBS>
<f1>97067.0</f1>
<f2>450.0</f2>
<f3>99598.0</f3>
</Summary></Run>
</Algorithm>
</Problem>
<Problem name = 'MONRP_50_4_5_4_90 100'>
<Algorithm name = 'NSGAII'>
<Run id = '1'>
<Summary>
<NumEvals>4000</NumEvals>
<RunTime>56.9393250942</RunTime>
<IBD>1.34823910793</IBD>
<IBS>0.0266238383332</IBS>
<f1>95919.0</f1>
<f2>437.0</f2>
<f3>99575.0</f3>
</Summary></Run>
<Run id = '2'>
<Summary>
<NumEvals>4000</NumEvals>
<RunTime>132.224381924</RunTime>
<IBD>1.34491537075</IBD>
<IBS>0.0183235571786</IBS>
<f1>96301.0</f1>
<f2>444.0</f2>
<f3>99588.0</f3>
</Summary></Run>
<Run id = '3'>
<Summary>
<NumEvals>4000</NumEvals>
<RunTime>12.7432048321</RunTime>
<IBD>1.34995452614</IBD>
<IBS>0.0358102496696</IBS>
<f1>96399.0</f1>
<f2>431.0</f2>
<f3>99615.0</f3>
</Summary></Run>
<Run id = '4'>
<Summary>
<NumEvals>4000</NumEvals>
<RunTime>19.6719181538</RunTime>
<IBD>1.34506295023</IBD>
<IBS>0.0242595554503</IBS>
<f1>96302.0</f1>
<f2>422.0</f2>
<f3>99589.0</f3>
</Summary></Run>
<Run id = '5'>
<Summary>
<NumEvals>4000</NumEvals>
<RunTime>35.99736619</RunTime>
<IBD>1.34406445719</IBD>
<IBS>0.0332326786304</IBS>
<f1>96070.0</f1>
<f2>439.0</f2>
<f3>99598.0</f3>
</Summary></Run>
<Run id = '6'>
<Summary>
<NumEvals>4000</NumEvals>
<RunTime>28.5630950928</RunTime>
<IBD>1.34817183411</IBD>
<IBS>0.029646891039</IBS>
<f1>96227.0</f1>
<f2>431.0</f2>
<f3>99578.0</f3>
</Summary></Run>
<Run id = '7'>
<Summary>
<NumEvals>4000</NumEvals>
<RunTime>7.33099079132</RunTime>
<IBD>1.35126619656</IBD>
<IBS>0.0350714583235</IBS>
<f1>96263.0</f1>
<f2>438.0</f2>
<f3>99581.0</f3>
</Summary></Run>
<Run id = '8'>
<Summary>
<NumEvals>4000</NumEvals>
<RunTime>31.5950539112</RunTime>
<IBD>1.35164619355</IBD>
<IBS>0.0387251356039</IBS>
<f1>96183.0</f1>
<f2>435.0</f2>
<f3>99581.0</f3>
</Summary></Run>
<Run id = '9'>
<Summary>
<NumEvals>4000</NumEvals>
<RunTime>128.474211931</RunTime>
<IBD>1.34229389685</IBD>
<IBS>0.0161815300463</IBS>
<f1>96272.0</f1>
<f2>440.0</f2>
<f3>99594.0</f3>
</Summary></Run>
<Run id = '10'>
<Summary>
<NumEvals>4000</NumEvals>
<RunTime>48.3125739098</RunTime>
<IBD>1.3511546308</IBD>
<IBS>0.0348888762451</IBS>
<f1>96412.0</f1>
<f2>443.0</f2>
<f3>99593.0</f3>
</Summary></Run>
</Algorithm>
<Algorithm name = 'SPEA2'>
<Run id = '1'>
<Summary>
<NumEvals>4000</NumEvals>
<RunTime>111.786090851</RunTime>
<IBD>1.34242077352</IBD>
<IBS>0.0263551906242</IBS>
<f1>96637.0</f1>
<f2>409.0</f2>
<f3>99623.0</f3>
</Summary></Run>
<Run id = '2'>
<Summary>
<NumEvals>4000</NumEvals>
<RunTime>95.2542378902</RunTime>
<IBD>1.3507928787</IBD>
<IBS>0.0390543449722</IBS>
<f1>96582.0</f1>
<f2>425.0</f2>
<f3>99606.0</f3>
</Summary></Run>
<Run id = '3'>
<Summary>
<NumEvals>4000</NumEvals>
<RunTime>106.208323956</RunTime>
<IBD>1.34614510656</IBD>
<IBS>0.0276457858297</IBS>
<f1>96565.0</f1>
<f2>405.0</f2>
<f3>99633.0</f3>
</Summary></Run>
<Run id = '4'>
<Summary>
<NumEvals>4000</NumEvals>
<RunTime>95.5198860168</RunTime>
<IBD>1.34253826156</IBD>
<IBS>0.0264459189053</IBS>
<f1>96532.0</f1>
<f2>404.0</f2>
<f3>99612.0</f3>
</Summary></Run>
<Run id = '5'>
<Summary>
<NumEvals>4000</NumEvals>
<RunTime>99.3248519897</RunTime>
<IBD>1.34927957321</IBD>
<IBS>0.0299059000905</IBS>
<f1>96660.0</f1>
<f2>403.0</f2>
<f3>99597.0</f3>
</Summary></Run>
<Run id = '6'>
<Summary>
<NumEvals>4000</NumEvals>
<RunTime>98.9073300362</RunTime>
<IBD>1.343719331</IBD>
<IBS>0.0353429724814</IBS>
<f1>96814.0</f1>
<f2>399.0</f2>
<f3>99638.0</f3>
</Summary></Run>
<Run id = '7'>
<Summary>
<NumEvals>4000</NumEvals>
<RunTime>112.358813047</RunTime>
<IBD>1.34526513001</IBD>
<IBS>0.0269907512186</IBS>
<f1>96195.0</f1>
<f2>429.0</f2>
<f3>99583.0</f3>
</Summary></Run>
<Run id = '8'>
<Summary>
<NumEvals>4000</NumEvals>
<RunTime>48.3815078735</RunTime>
<IBD>1.34913113703</IBD>
<IBS>0.0295369883311</IBS>
<f1>96123.0</f1>
<f2>426.0</f2>
<f3>99596.0</f3>
</Summary></Run>
<Run id = '9'>
<Summary>
<NumEvals>4000</NumEvals>
<RunTime>91.89523983</RunTime>
<IBD>1.34418182203</IBD>
<IBS>0.0232585462866</IBS>
<f1>96464.0</f1>
<f2>428.0</f2>
<f3>99590.0</f3>
</Summary></Run>
<Run id = '10'>
<Summary>
<NumEvals>4000</NumEvals>
<RunTime>42.6459658146</RunTime>
<IBD>1.33977921106</IBD>
<IBS>0.0395502921658</IBS>
<f1>96946.0</f1>
<f2>395.0</f2>
<f3>99652.0</f3>
</Summary></Run>
</Algorithm>
</Problem>
<Problem name = 'MONRP_50_4_5_4_110 100'>
<Algorithm name = 'NSGAII'>
<Run id = '1'>
<Summary>
<NumEvals>4000</NumEvals>
<RunTime>40.5767550468</RunTime>
<IBD>1.35403311981</IBD>
<IBS>0.0217278340707</IBS>
<f1>97038.0</f1>
<f2>480.0</f2>
<f3>99535.0</f3>
</Summary></Run>
<Run id = '2'>
<Summary>
<NumEvals>4000</NumEvals>
<RunTime>79.8823640347</RunTime>
<IBD>1.35499516597</IBD>
<IBS>0.0208711937721</IBS>
<f1>96976.0</f1>
<f2>487.0</f2>
<f3>99527.0</f3>
</Summary></Run>
<Run id = '3'>
<Summary>
<NumEvals>4000</NumEvals>
<RunTime>55.7409749031</RunTime>
<IBD>1.36404137931</IBD>
<IBS>0.0226229420748</IBS>
<f1>96985.0</f1>
<f2>507.0</f2>
<f3>99509.0</f3>
</Summary></Run>
<Run id = '4'>
<Summary>
<NumEvals>4000</NumEvals>
<RunTime>13.0148692131</RunTime>
<IBD>1.35868392194</IBD>
<IBS>0.0243489365945</IBS>
<f1>96700.0</f1>
<f2>501.0</f2>
<f3>99502.0</f3>
</Summary></Run>
<Run id = '5'>
<Summary>
<NumEvals>4000</NumEvals>
<RunTime>43.8718781471</RunTime>
<IBD>1.35855570194</IBD>
<IBS>0.0164156201107</IBS>
<f1>96815.0</f1>
<f2>510.0</f2>
<f3>99518.0</f3>
</Summary></Run>
<Run id = '6'>
<Summary>
<NumEvals>4000</NumEvals>
<RunTime>7.34009408951</RunTime>
<IBD>1.3560207552</IBD>
<IBS>0.0271653011689</IBS>
<f1>97306.0</f1>
<f2>470.0</f2>
<f3>99532.0</f3>
</Summary></Run>
<Run id = '7'>
<Summary>
<NumEvals>4000</NumEvals>
<RunTime>23.6109719276</RunTime>
<IBD>1.35426438775</IBD>
<IBS>0.0299962382467</IBS>
<f1>97127.0</f1>
<f2>470.0</f2>
<f3>99522.0</f3>
</Summary></Run>
<Run id = '8'>
<Summary>
<NumEvals>4000</NumEvals>
<RunTime>24.023542881</RunTime>
<IBD>1.35368680762</IBD>
<IBS>0.0293953522017</IBS>
<f1>97156.0</f1>
<f2>446.0</f2>
<f3>99546.0</f3>
</Summary></Run>
<Run id = '9'>
<Summary>
<NumEvals>4000</NumEvals>
<RunTime>13.2759559155</RunTime>
<IBD>1.35554912247</IBD>
<IBS>0.027624756933</IBS>
<f1>96897.0</f1>
<f2>478.0</f2>
<f3>99538.0</f3>
</Summary></Run>
<Run id = '10'>
<Summary>
<NumEvals>4000</NumEvals>
<RunTime>45.9646551609</RunTime>
<IBD>1.36066857351</IBD>
<IBS>0.023232055971</IBS>
<f1>97018.0</f1>
<f2>490.0</f2>
<f3>99525.0</f3>
</Summary></Run>
</Algorithm>
<Algorithm name = 'SPEA2'>
<Run id = '1'>
<Summary>
<NumEvals>4000</NumEvals>
<RunTime>53.1780099869</RunTime>
<IBD>1.35926195038</IBD>
<IBS>0.0218257073154</IBS>
<f1>96704.0</f1>
<f2>502.0</f2>
<f3>99510.0</f3>
</Summary></Run>
<Run id = '2'>
<Summary>
<NumEvals>4000</NumEvals>
<RunTime>61.4563601017</RunTime>
<IBD>1.35602692888</IBD>
<IBS>0.0195768947523</IBS>
<f1>96800.0</f1>
<f2>498.0</f2>
<f3>99528.0</f3>
</Summary></Run>
<Run id = '3'>
<Summary>
<NumEvals>4000</NumEvals>
<RunTime>50.9793438911</RunTime>
<IBD>1.35697957402</IBD>
<IBS>0.0240621218906</IBS>
<f1>97155.0</f1>
<f2>450.0</f2>
<f3>99556.0</f3>
</Summary></Run>
<Run id = '4'>
<Summary>
<NumEvals>4000</NumEvals>
<RunTime>67.5623788834</RunTime>
<IBD>1.35833297399</IBD>
<IBS>0.0200170979137</IBS>
<f1>97143.0</f1>
<f2>479.0</f2>
<f3>99516.0</f3>
</Summary></Run>
<Run id = '5'>
<Summary>
<NumEvals>4000</NumEvals>
<RunTime>55.2503540516</RunTime>
<IBD>1.35991055414</IBD>
<IBS>0.0236161360583</IBS>
<f1>97024.0</f1>
<f2>481.0</f2>
<f3>99525.0</f3>
</Summary></Run>
<Run id = '6'>
<Summary>
<NumEvals>4000</NumEvals>
<RunTime>48.7421588898</RunTime>
<IBD>1.35611698584</IBD>
<IBS>0.0238677996156</IBS>
<f1>96999.0</f1>
<f2>458.0</f2>
<f3>99555.0</f3>
</Summary></Run>
<Run id = '7'>
<Summary>
<NumEvals>4000</NumEvals>
<RunTime>71.7556648254</RunTime>
<IBD>1.35461501464</IBD>
<IBS>0.0236923633628</IBS>
<f1>97157.0</f1>
<f2>449.0</f2>
<f3>99555.0</f3>
</Summary></Run>
<Run id = '8'>
<Summary>
<NumEvals>4000</NumEvals>
<RunTime>65.9363629818</RunTime>
<IBD>1.35262704396</IBD>
<IBS>0.0157789527314</IBS>
<f1>97246.0</f1>
<f2>475.0</f2>
<f3>99575.0</f3>
</Summary></Run>
<Run id = '9'>
<Summary>
<NumEvals>4000</NumEvals>
<RunTime>67.6292550564</RunTime>
<IBD>1.35842090437</IBD>
<IBS>0.0207683064476</IBS>
<f1>96905.0</f1>
<f2>470.0</f2>
<f3>99546.0</f3>
</Summary></Run>
<Run id = '10'>
<Summary>
<NumEvals>4000</NumEvals>
<RunTime>53.1840829849</RunTime>
<IBD>1.36116771021</IBD>
<IBS>0.0245732160157</IBS>
<f1>97309.0</f1>
<f2>467.0</f2>
<f3>99569.0</f3>
</Summary></Run>
</Algorithm>
</Problem>
</Experiment>
